whylog/__init__.py
whylog/src/__init__.py
whylog/src/whylog.py
whylog-0.1.dist-info/LICENSE
whylog-0.1.dist-info/METADATA
whylog-0.1.dist-info/WHEEL
whylog-0.1.dist-info/top_level.txt
whylog-0.1.dist-info/RECORD
