Metadata-Version: 2.1
Name: whylog
Version: 0.1
Summary: Prints out a log message to terminal in color
Home-page: https://github.com/iamlrk/whylog
Author-email: <lepakshiramkiran@hotmail.com>
Keywords: python,logging,log,print
Classifier: License :: OSI Approved :: MIT License
Classifier: Development Status :: 4 - Beta
Classifier: Programming Language :: Python :: 3
Classifier: Operating System :: OS Independent
License-File: LICENSE
